witrnhid/__init__.py
witrnhid/core.py
witrnhid/core.pyi
witrnhid-1.1.4.dist-info/licenses/LICENSE
witrnhid-1.1.4.dist-info/METADATA
witrnhid-1.1.4.dist-info/WHEEL
witrnhid-1.1.4.dist-info/top_level.txt
witrnhid-1.1.4.dist-info/RECORD
