Metadata-Version: 2.4
Name: witrnhid
Version: 1.1.4
Summary: A Python API for WITRN HID devices.
Author-email: JohnScott <ruaorz@gmail.com>
License: LGPL-3.0-or-later
Project-URL: Homepage, https://github.com/JohnScotttt/WITRN_HID_API
Requires-Python: >=3.10
License-File: LICENSE
Requires-Dist: hidapi>=0.14.0
Requires-Dist: usbpdparser==1.1.4
Dynamic: license-file
